swotted/__init__.py
swotted/decomposition_contraints.py
swotted/fastswotted.py
swotted/loss_metrics.py
swotted/slidingWindow_model.py
swotted/swotted.py
swotted/temporal_regularization.py
swotted/utils.py
swotted-1.0.1.dist-info/LICENSE
swotted-1.0.1.dist-info/METADATA
swotted-1.0.1.dist-info/WHEEL
swotted-1.0.1.dist-info/RECORD
